Workbook
Name salario: APP!$F$29
Name rendimento_carteira: APP!$F$30
Name sugestao_investimento: APP!$F$31
Name aporte: APP!$F$35
Name qtd_anos: APP!$F$36
Name taxa_mensal: APP!$F$37
Name patrimonio: APP!$F$38
Name dividendo_mensais: APP!$F$39
Name aporte: [1]APP!$D$17
Name patrimonio: [1]APP!$D$20
Name qtd_anos: [1]APP!$D$18
Name rendimento_carteira: [1]APP!$D$13
Name salario: [1]APP!$D$12
Name sugestao_investimento: [1]APP!$D$14
Name taxa_mensal: [1]APP!$D$19

Sheet APP
B28: Configurações
B29: Salário | F29: 2000
B30: Rendimento Carteira | F30: 0.006
B31: Sugestão | F31: =F29*30% -> 600
B34: Investimento Mensal
B35: Quanto investir por mês ? | F35: 200
B36: Por Quantos Anos ? | F36: 5
B37: Taxa de Rendimento mensal ? | F37: 0.01079
B38: Patrimônio acumulado ? | F38: =FV(taxa_mensal,qtd_anos*12,aporte*-1) -> 16755.383
B39: Dividendos Mensais ? | F39: =patrimonio*rendimento_carteira -> 100.5323
B41: Cenários | F41: Valor arecadado | H41: Dividendo
A42: 2 | B42: Quanto em 2 Anos ? | F42: =FV($F$37,$A42*12,$F$35*-1) -> 5445.5255 | H42: =F42*rendimento_carteira -> 32.673153
A43: 5 | B43: Quanto em 5 Anos ? | F43: =FV($F$37,$A43*12,$F$35*-1) -> 16755.383 | H43: =F43*rendimento_carteira -> 100.5323
A44: 10 | B44: Quanto em 10 Anos ? | F44: =FV($F$37,$A44*12,$F$35*-1) -> 48656.843 | H44: =F44*rendimento_carteira -> 291.94106
A45: 20 | B45: Quanto em 20 Anos ? | F45: =FV($F$37,$A45*12,$F$35*-1) -> 225039.68 | H45: =F45*rendimento_carteira -> 1350.2381
A46: 30 | B46: Quanto em 30 Anos ? | F46: =FV($F$37,$A46*12,$F$35*-1) -> 864433.93 | H46: =F46*rendimento_carteira -> 5186.6036
B48: PERFIL | F48: Moderado
B49: VALOR A SER INVESTIDO POR MÊS | F49: =aporte -> 200
B51: TIPO DE FII | F51: Percentual Sugerido | H51: Valores
B52: PAPEL | F52: =VLOOKUP($F$48&"-"&B52,Planilha2!$A:$D,4,FALSE) -> 0.32 | H52: =F52*$F$49 -> 64
B53: TIJOLO | F53: =VLOOKUP($F$48&"-"&B53,Planilha2!$A:$D,4,FALSE) -> 0.35 | H53: =F53*$F$49 -> 70
B54: HÍBRIDOS | F54: =VLOOKUP($F$48&"-"&B54,Planilha2!$A:$D,4,FALSE) -> 0.08 | H54: =F54*$F$49 -> 16
B55: FOFs | F55: =VLOOKUP($F$48&"-"&B55,Planilha2!$A:$D,4,FALSE) -> 0.05 | H55: =F55*$F$49 -> 10
B56: DESENVOLVIMENTO | F56: =VLOOKUP($F$48&"-"&B56,Planilha2!$A:$D,4,FALSE) -> 0.1 | H56: =F56*$F$49 -> 20
B57: HOTELARIAS | F57: =VLOOKUP($F$48&"-"&B57,Planilha2!$A:$D,4,FALSE) -> 0.1 | H57: =F57*$F$49 -> 20
H58: =SUM(H52:I57) -> 200

Sheet Planilha2
A2: CHAVE | B2: PERFIL | C2: TIPO DE FII | D2: %
A3: =B3&"-"&C3 -> Conservador-PAPEL | B3: Conservador | C3: PAPEL | D3: 0.3 | G3: %
A4: =B4&"-"&C4 -> Conservador-TIJOLO | B4: Conservador | C4: TIJOLO | D4: 0.5 | F4: Moderado-TIJOLO | G4: =VLOOKUP(F4,$A:$D,4,FALSE) -> 0.35
A5: =B5&"-"&C5 -> Conservador-HÍBRIDOS | B5: Conservador | C5: HÍBRIDOS | D5: 0.1
A6: =B6&"-"&C6 -> Conservador-FOFs | B6: Conservador | C6: FOFs | D6: 0.1
A7: =B7&"-"&C7 -> Conservador-DESENVOLVIMENTO | B7: Conservador | C7: DESENVOLVIMENTO | D7: 0
A8: =B8&"-"&C8 -> Conservador-HOTELARIAS | B8: Conservador | C8: HOTELARIAS | D8: 0
A9: =B9&"-"&C9 -> Moderado-PAPEL | B9: Moderado | C9: PAPEL | D9: 0.32
A10: =B10&"-"&C10 -> Moderado-TIJOLO | B10: Moderado | C10: TIJOLO | D10: 0.35
A11: =B11&"-"&C11 -> Moderado-HÍBRIDOS | B11: Moderado | C11: HÍBRIDOS | D11: 0.08
A12: =B12&"-"&C12 -> Moderado-FOFs | B12: Moderado | C12: FOFs | D12: 0.05
A13: =B13&"-"&C13 -> Moderado-DESENVOLVIMENTO | B13: Moderado | C13: DESENVOLVIMENTO | D13: 0.1
A14: =B14&"-"&C14 -> Moderado-HOTELARIAS | B14: Moderado | C14: HOTELARIAS | D14: 0.1
A15: =B15&"-"&C15 -> Agressivo-PAPEL | B15: Agressivo | C15: PAPEL | D15: 0.5
A16: =B16&"-"&C16 -> Agressivo-TIJOLO | B16: Agressivo | C16: TIJOLO | D16: 0.1
... A20: =B20&"-"&C20 -> Agressivo-HOTELARIAS | B20: Agressivo | C20: HOTELARIAS | D20: 0.1
